{
"type": "FeatureCollection",
"name": "gate",
"crs": { "type": "name", "properties": { "name": "urn:ogc:def:crs:OGC:1.3:CRS84" } },
"features": [
{ "type": "Feature", "properties": { "name": "GAT", "folders": "", "description": "", "altitude": 9.291804, "alt_mode": "", "time_begin": "", "time_end": "", "time_when": "" }, "geometry": { "type": "Point", "coordinates": [ -122.422193, 47.666592, 9.291804 ] } }
]
}
