{
"type": "FeatureCollection",
"name": "rest_rooms",
"crs": { "type": "name", "properties": { "name": "urn:ogc:def:crs:OGC:1.3:CRS84" } },
"features": [
{ "type": "Feature", "properties": { "name": "rest room", "folders": "", "description": "", "altitude": 0.0, "alt_mode": "", "time_begin": "", "time_end": "", "time_when": "" }, "geometry": { "type": "Point", "coordinates": [ -122.4279318, 47.6609519, 0.0 ] } },
{ "type": "Feature", "properties": { "name": "rest room", "folders": "", "description": "", "altitude": 0.0, "alt_mode": "", "time_begin": "", "time_end": "", "time_when": "" }, "geometry": { "type": "Point", "coordinates": [ -122.4184368, 47.654672, 0.0 ] } }
]
}
