{
"type": "FeatureCollection",
"name": "bridges",
"crs": { "type": "name", "properties": { "name": "urn:ogc:def:crs:OGC:1.3:CRS84" } },
"features": [
{ "type": "Feature", "properties": { "name": "bridge", "folders": "", "description": "", "altitude": 0.0, "alt_mode": "", "time_begin": "", "time_end": "", "time_when": "" }, "geometry": { "type": "Point", "coordinates": [ -122.3996778, 47.573828, 0.0 ] } },
{ "type": "Feature", "properties": { "name": "bridge", "folders": "", "description": "", "altitude": 0.0, "alt_mode": "", "time_begin": "", "time_end": "", "time_when": "" }, "geometry": { "type": "Point", "coordinates": [ -122.4027034, 47.5774863, 0.0 ] } },
{ "type": "Feature", "properties": { "name": "bridge", "folders": "", "description": "", "altitude": 0.0, "alt_mode": "", "time_begin": "", "time_end": "", "time_when": "" }, "geometry": { "type": "Point", "coordinates": [ -122.3999139, 47.5745044, 0.0 ] } }
]
}
