{
"type": "FeatureCollection",
"name": "parking_lot_symbols",
"crs": { "type": "name", "properties": { "name": "urn:ogc:def:crs:OGC:1.3:CRS84" } },
"features": [
{ "type": "Feature", "properties": { "name": "parking lot", "folders": "", "description": "", "altitude": 0.0, "alt_mode": "", "time_begin": "", "time_end": "", "time_when": "" }, "geometry": { "type": "Point", "coordinates": [ -121.710155, 47.4867, 0.0 ] } },
{ "type": "Feature", "properties": { "name": "parking lot", "folders": "", "description": "", "altitude": 0.0, "alt_mode": "", "time_begin": "", "time_end": "", "time_when": "" }, "geometry": { "type": "Point", "coordinates": [ -121.7231802, 47.4876073, 0.0 ] } },
{ "type": "Feature", "properties": { "name": "parking lot", "folders": "", "description": "", "altitude": 0.0, "alt_mode": "", "time_begin": "", "time_end": "", "time_when": "" }, "geometry": { "type": "Point", "coordinates": [ -121.757299, 47.487602, 0.0 ] } },
{ "type": "Feature", "properties": { "name": "parking lot", "folders": "", "description": "", "altitude": 0.0, "alt_mode": "", "time_begin": "", "time_end": "", "time_when": "" }, "geometry": { "type": "Point", "coordinates": [ -121.7538578, 47.486703, 0.0 ] } }
]
}
